{"nodes": [{"id": "onboardingauth_component", "label": "OnboardingAuth", "file_type": "code", "source_file": "components/ui/onboarding-auth.tsx", "source_location": null, "source_url": null, "captured_at": null, "author": null, "contributor": null}, {"id": "ui_onboarding_auth", "label": "OnboardingAuth Guard Component", "file_type": "code", "source_file": "components/ui/onboarding-auth.tsx", "source_location": null, "source_url": null, "captured_at": null, "author": null, "contributor": null}, {"id": "auth_localstorage", "label": "Auth via localStorage (accessToken, tenantId)", "file_type": "code", "source_file": "components/ui/onboarding-auth.tsx", "source_location": null, "source_url": null, "captured_at": null, "author": null, "contributor": null}], "edges": [{"source": "ui_onboarding_auth", "target": "auth_localstorage", "relation": "references", "confidence": "EXTRACTED", "confidence_score": 1.0, "source_file": "components/ui/onboarding-auth.tsx", "source_location": null, "weight": 1.0}, {"source": "ui_onboarding_auth", "target": "ui_sidebar", "relation": "conceptually_related_to", "confidence": "INFERRED", "confidence_score": 0.65, "source_file": "components/ui/onboarding-auth.tsx", "source_location": null, "weight": 0.65}], "hyperedges": []}